LICENSE
README.md
setup.py
SearchDb/SearchDb.py
SearchDb/__init__.py
SearchDb.egg-info/PKG-INFO
SearchDb.egg-info/SOURCES.txt
SearchDb.egg-info/dependency_links.txt
SearchDb.egg-info/top_level.txt