Metadata-Version: 2.1
Name: SearchDb
Version: 1.0.1
Summary: Python dictionary backed by SQLite, includes fast text search and more advanced data structures
Home-page: https://github.com/cpuboi/SearchDb
Author: cpuboi
License: GPLv2
Keywords: SQLite,dictionary,text search
Classifier: Development Status :: 4 - Beta
Requires-Python: >=3.9
License-File: LICENSE
